{
  "version": 1,
  "planId": "1781432968570-phase-1-python-rust-1-1-api-gap-audits",
  "createdAt": "2026-06-14T10:29:28.570Z",
  "updatedAt": "2026-06-14T10:38:35.319Z",
  "briefPath": ".omc/ultragoal/plans/1781432968570-phase-1-python-rust-1-1-api-gap-audits/brief.md",
  "goalsPath": ".omc/ultragoal/plans/1781432968570-phase-1-python-rust-1-1-api-gap-audits/goals.json",
  "ledgerPath": ".omc/ultragoal/plans/1781432968570-phase-1-python-rust-1-1-api-gap-audits/ledger.jsonl",
  "claudeGoalMode": "aggregate",
  "goals": [
    {
      "id": "G001-a1",
      "title": "A1",
      "objective": "ccb-agents API gap audit — diff Python agents/+rolepacks/ public symbols vs ccb-agents pub items; write docs/gap-reports/ccb-agents.md",
      "status": "complete",
      "attempt": 1,
      "createdAt": "2026-06-14T10:29:28.570Z",
      "updatedAt": "2026-06-14T10:33:19.518Z",
      "startedAt": "2026-06-14T10:33:04.970Z",
      "completedAt": "2026-06-14T10:33:19.518Z",
      "evidence": "docs/gap-reports/ccb-agents.md written; 0/133 name-level gaps; 198 Rust pub items"
    },
    {
      "id": "G002-a2",
      "title": "A2",
      "objective": "ccb-memory API gap audit — diff Python memory/+project_memory/ vs ccb-memory; write docs/gap-reports/ccb-memory.md",
      "status": "complete",
      "attempt": 1,
      "createdAt": "2026-06-14T10:29:28.570Z",
      "updatedAt": "2026-06-14T10:37:25.434Z",
      "startedAt": "2026-06-14T10:37:25.269Z",
      "completedAt": "2026-06-14T10:37:25.434Z",
      "evidence": "docs/gap-reports/2.md written"
    },
    {
      "id": "G003-a3",
      "title": "A3",
      "objective": "ccb-providers API gap audit — diff Python provider_backends/+provider_execution/+provider_runtime/+opencode_runtime/ vs ccb-providers; write docs/gap-reports/ccb-providers.md",
      "status": "complete",
      "attempt": 1,
      "createdAt": "2026-06-14T10:29:28.570Z",
      "updatedAt": "2026-06-14T10:37:25.756Z",
      "startedAt": "2026-06-14T10:37:25.596Z",
      "completedAt": "2026-06-14T10:37:25.756Z",
      "evidence": "docs/gap-reports/3.md written"
    },
    {
      "id": "G004-a4",
      "title": "A4",
      "objective": "ccb-daemon API gap audit — diff Python ccbd/ vs ccb-daemon control plane + handlers; write docs/gap-reports/ccb-daemon.md",
      "status": "complete",
      "attempt": 1,
      "createdAt": "2026-06-14T10:29:28.570Z",
      "updatedAt": "2026-06-14T10:37:26.077Z",
      "startedAt": "2026-06-14T10:37:25.917Z",
      "completedAt": "2026-06-14T10:37:26.077Z",
      "evidence": "docs/gap-reports/4.md written"
    },
    {
      "id": "G005-a5",
      "title": "A5",
      "objective": "ccb-cli API gap audit — diff Python cli/+ask_cli/ vs ccb-cli; write docs/gap-reports/ccb-cli.md",
      "status": "complete",
      "attempt": 1,
      "createdAt": "2026-06-14T10:29:28.570Z",
      "updatedAt": "2026-06-14T10:38:35.319Z",
      "startedAt": "2026-06-14T10:37:26.240Z",
      "evidence": "5 gap reports; Phase 1 complete",
      "completedAt": "2026-06-14T10:38:35.319Z"
    }
  ],
  "claudeObjective": "Complete all ultragoal stories in .omc/ultragoal/plans/1781432968570-phase-1-python-rust-1-1-api-gap-audits/goals.json: G001-a1 A1; G002-a2 A2; G003-a3 A3; G004-a4 A4; G005-a5 A5"
}
