{
  "id": "06-25-py2rust-wave5-daemon-restore-jobs",
  "name": "06-25-py2rust-wave5-daemon-restore-jobs",
  "title": "Wave 5: daemon restart job continuity",
  "description": "Daemon restart must reload persisted running jobs into execution/heartbeat so trace shows them and heartbeat can drive them to completion.",
  "status": "completed",
  "dev_type": null,
  "scope": null,
  "package": null,
  "priority": "P0",
  "creator": "luck",
  "assignee": "kimi2.7",
  "createdAt": "2026-06-25",
  "completedAt": "2026-06-25",
  "branch": null,
  "base_branch": "python-rust/rolepacks-versioning-translation",
  "worktree_path": null,
  "commit": null,
  "pr_url": null,
  "subtasks": [],
  "children": [],
  "parent": "06-24-py2rust-remaining-parity",
  "relatedFiles": [],
  "notes": "",
  "meta": {}
}