{
  "id": "py2rust-wave5-parity-sweep",
  "name": "py2rust-wave5-parity-sweep",
  "title": "Wave 5: parity sweep — P1/P2 gap 批量闭环 + 矩阵扫雷",
  "description": "Batch-close the repetitive py->rust parity grind: 6 untasked Wave 5 gaps (midrun-cancel/provider-timeout/auth-error-surface/rich-ping/codex-delivery-guard/start-foreground-service) + sweep plans/rust-python-test-parity-matrix.md partial/gap/missing items, using a unified per-item closure template. Goal: 1:1 Rust replacement, ccbr runs as ccb.",
  "status": "planning",
  "dev_type": null,
  "scope": null,
  "package": null,
  "priority": "P1",
  "creator": "luck",
  "assignee": "kimi2.7",
  "createdAt": "2026-06-25",
  "completedAt": null,
  "branch": null,
  "base_branch": "python-rust/rolepacks-versioning-translation",
  "worktree_path": null,
  "commit": null,
  "pr_url": null,
  "subtasks": [],
  "children": [],
  "parent": "06-24-py2rust-remaining-parity",
  "relatedFiles": [],
  "notes": "",
  "meta": {}
}